eveauth/__init__.py
eveauth/main.py
python_eveauth-0.1.0b2.dist-info/licenses/LICENSE
python_eveauth-0.1.0b2.dist-info/WHEEL
python_eveauth-0.1.0b2.dist-info/METADATA
python_eveauth-0.1.0b2.dist-info/RECORD
