Metadata-Version: 2.4
Name: python-eveauth
Version: 0.1.0b2
Summary: A library for authorizing desktop apps with the EVE online SSO.
Author-email: Erik Kalkoken <kalkoken87@gmail.com>
Requires-Python: >=3.10
Classifier: Intended Audience :: Developers
Classifier: License :: OSI Approved :: MIT License
Classifier: Natural Language :: English
Classifier: Operating System :: OS Independent
Classifier: Programming Language :: Python
Classifier: Programming Language :: Python :: 3
Classifier: Programming Language :: Python :: 3.10
Classifier: Programming Language :: Python :: 3.11
Classifier: Programming Language :: Python :: 3.12
Classifier: Programming Language :: Python :: 3.13
Classifier: Topic :: Communications :: Chat
Classifier: Topic :: Software Development :: Libraries
Classifier: Topic :: Software Development :: Libraries :: Python Modules
License-File: LICENSE
Requires-Dist: requests
Requires-Dist: python-jose
Requires-Dist: requests-mock ; extra == "test"
Requires-Dist: coverage ; extra == "test"
Project-URL: Homepage, https://github.com/ErikKalkoken/python-eveauth
Project-URL: Source, https://github.com/ErikKalkoken/python-eveauth
Project-URL: Tracker, https://github.com/ErikKalkoken/python-eveauth/issues
Provides-Extra: test
